setup.cfg
setup.py
pdnsbe/__init__.py
pdnsbe/backend.py
pdnsbe/core.py
pdnsbe.egg-info/PKG-INFO
pdnsbe.egg-info/SOURCES.txt
pdnsbe.egg-info/dependency_links.txt
pdnsbe.egg-info/pbr.json
pdnsbe.egg-info/top_level.txt