Metadata-Version: 1.1
Name: pdnsbe
Version: 0.9.8
Summary: Library to easily implement and run a python PowerDNS socket
Home-page: https://github.com/wimtie/pdnsbe
Author: Tim Lamballais Tessensohn
Author-email: tim@wimtie.org
License: UNKNOWN
Download-URL: https://github.com/wimtie/pdnsbe/tarball/0.9.8
Keywords: PowerDNS,backend,python,generic,pluggable
Platform: UNKNOWN
